stepscribe/__init__.py
stepscribe/state_machine.py
stepscribe/version.py
stepscribe/components/__init__.py
stepscribe/components/catcher.py
stepscribe/components/choice_rules.py
stepscribe/components/item_processor.py
stepscribe/components/item_reader.py
stepscribe/components/result_writer.py
stepscribe/components/retrier.py
stepscribe/states/__init__.py
stepscribe/states/base_state.py
stepscribe/states/choice.py
stepscribe/states/map.py
stepscribe/states/parallel.py
stepscribe/states/pass_wait.py
stepscribe/states/succeed_fail.py
stepscribe/states/task.py
stepscribe-0.0.5.dist-info/licenses/LICENSE
stepscribe-0.0.5.dist-info/WHEEL
stepscribe-0.0.5.dist-info/METADATA
stepscribe-0.0.5.dist-info/RECORD
