Metadata-Version: 2.4
Name: stepscribe
Version: 0.0.5
Summary: Write AWS Step Function State Machines in python and export to AWS States Language JSON. Allows for easy reuse of states or state components as well as generating complex state machines from simple pieces. Integrates with other tools like Pulumi to easily have a single python definition of the state machine that can generate specific JSON for multiple AWS environments.
Author-email: Jason Preszler <jpreszler+stepscribe@gmail.com>
Requires-Python: >=3.12
License-File: LICENSE
Requires-Dist: boto3>=1.42.14
Project-URL: Bug Reports, https://github.com/DataVimDev/StepScribe/issues
Project-URL: Homepage, https://github.com/DataVimDev/StepScribe
Project-URL: Source, https://github.com/DataVimDev/StepScribe
